zstatspython/__init__.py
zstatspython/zstatspy.py
zstatspython-1.1.dist-info/LICENSE
zstatspython-1.1.dist-info/METADATA
zstatspython-1.1.dist-info/WHEEL
zstatspython-1.1.dist-info/top_level.txt
zstatspython-1.1.dist-info/RECORD
