Metadata-Version: 2.1
Name: zstatspython
Version: 1.1
Summary: Get Player Data From zstats plugin. Not An Official Plugin
Home-page: https://github.com/Astrogamer54/zstatspython
Author: Astrogamer54
Author-email: mail@astrogamer54.com
License: UNKNOWN
Project-URL: Bug Tracker, https://github.com/Astrogamer54/zstatspython/issues
Platform: UNKNOWN
Classifier: Programming Language :: Python :: 3
Classifier: License :: OSI Approved :: MIT License
Classifier: Operating System :: OS Independent
Requires-Dist: mysql-connector-python
